Oxgram/__init__.py
Oxgram/exceptions/__init__.py
Oxgram/exceptions/exceptions.py
Oxgram/functions/__init__.py
Oxgram/functions/collections.py
Oxgram/functions/function01.py
Oxgram/functions/function02.py
Oxgram/functions/function03.py
Oxgram/functions/function04.py
Oxgram/functions/function05.py
Oxgram/functions/function06.py
Oxgram/scripts/__init__.py
Oxgram/scripts/script01.py
oxgram-0.0.10.dist-info/METADATA
oxgram-0.0.10.dist-info/WHEEL
oxgram-0.0.10.dist-info/top_level.txt
oxgram-0.0.10.dist-info/RECORD
